{
    "$schema": "http://json-schema.org/schema",
    "id": "GraphQlJazzSchematics",
    "title": "GraphQL Jazz Type Model Generator",
    "type": "object",
    "description": "",
    "properties": {
        "types": {
            "type": "boolean",
            "default": false,
            "description": "Generate types"
        },
        "variables": {
            "type": "boolean",
            "default": false,
            "description": "Generate variables"
        },
        "operations": {
            "type": "boolean",
            "default": false,
            "description": "Generate operations"
        },
        "limit": {
            "type": "number",
            "default": 1000,
            "description": "Amount of files created"
        },
        "offset": {
            "type": "number",
            "default": 0,
            "description": "Offset"
        }
    },
    "required": []
}
